cpu/register/bitregister.vhdl
library ieee;
use ieee.std_logic_1164.all;

entity bitregister is 
  generic (
    N : natural := 8
  );
  port (
    Rin , Clock, R_serial : in  std_logic;
    Q                     : out std_logic_vector(N - 1 downto 0)
  );
end bitregister;

architecture behavior of bitregister is

  signal Q_int : std_logic_vector(N - 1 downto 0);

  begin
    process
    begin
      wait until Clock'event and Clock = '1';
      if Rin = '1' then
        Q_int <= Q_int(N - 2 downto 0) & R_serial;
      end if ;
    end process;

    Q <= Q_int;
end behavior ;

register/bitregister_tb.vhdl
library ieee;
use ieee.std_logic_1164.all;

entity bitregister_tb is
end bitregister_tb;

architecture sim of bitregister_tb is

  constant N : natural := 8;

  signal Rin       : std_logic := '0';
  signal Clock     : std_logic := '0';
  signal R_serial  : std_logic := '0';
  signal Q         : std_logic_vector(N - 1 downto 0);

begin

  uut: entity work.bitregister
    generic map (
      N => N
    )
    port map (
      Rin      => Rin,
      Clock    => Clock,
      R_serial => R_serial,
      Q        => Q
    );

  clk_proc : process
  begin
    Clock <= '0';
    wait for 5 ns;
    Clock <= '1';
    wait for 5 ns;
  end process;

  stim_proc : process
  begin
    Rin <= '1';

    R_serial <= '1'; wait for 10 ns;
    R_serial <= '0'; wait for 10 ns;
    R_serial <= '1'; wait for 10 ns;
    R_serial <= '1'; wait for 10 ns;
    R_serial <= '0'; wait for 10 ns;
    R_serial <= '0'; wait for 10 ns;
    R_serial <= '1'; wait for 10 ns;
    R_serial <= '1'; wait for 10 ns;

    Rin <= '0';

    wait;
  end process;

end sim;

registrador/reg_serial.vcd
$date
  Thu Jan  8 01:42:45 2026
$end
$version
  GHDL v0
$end
$timescale
  1 fs
$end
$scope module standard $end
$upscope $end
$scope module std_logic_1164 $end
$upscope $end
$scope module bitregister_tb $end
$var reg 1 ! rin $end
$var reg 1 " clock $end
$var reg 1 # r_serial $end
$var reg 8 $ q[7:0] $end
$scope module uut $end
$var reg 1 % rin $end
$var reg 1 & clock $end
$var reg 1 ' r_serial $end
$var reg 8 ( q[7:0] $end
$var reg 8 ) q_int[7:0] $end
$upscope $end
$upscope $end
$enddefinitions $end
#0
1!
0"
1#
bUUUUUUUU $
1%
0&
1'
bUUUUUUUU (
bUUUUUUUU )
#5000000
1"
bUUUUUUU1 $
1&
bUUUUUUU1 (
bUUUUUUU1 )
#10000000
0"
0#
0&
0'
#15000000
1"
bUUUUUU10 $
1&
bUUUUUU10 (
bUUUUUU10 )
#20000000
0"
1#
0&
1'
#25000000
1"
bUUUUU101 $
1&
bUUUUU101 (
bUUUUU101 )
#30000000
0"
0&
#35000000
1"
bUUUU1011 $
1&
bUUUU1011 (
bUUUU1011 )
#40000000
0"
0#
0&
0'
#45000000
1"
bUUU10110 $
1&
bUUU10110 (
bUUU10110 )
#50000000
0"
0&
#55000000
1"
bUU101100 $
1&
bUU101100 (
bUU101100 )
#60000000
0"
1#
0&
1'
#65000000
1"
bU1011001 $
1&
bU1011001 (
bU1011001 )
#70000000
0"
0&
#75000000
1"
b10110011 $
1&
b10110011 (
b10110011 )
#80000000
0!
0"
0%
0&
